toomanyconfigs/__init__.py
toomanyconfigs/api.py
toomanyconfigs/core.py
toomanyconfigs/cwd.py
toomanyconfigs/simple_api.py
toomanyconfigs-0.2.868.dist-info/licenses/LICENSE
toomanyconfigs-0.2.868.dist-info/METADATA
toomanyconfigs-0.2.868.dist-info/WHEEL
toomanyconfigs-0.2.868.dist-info/RECORD
