Metadata-Version: 2.4
Name: toomanyconfigs
Version: 0.2.868
Summary: 
License-File: LICENSE
Author: Miles Copeland Luce
Requires-Python: >=3.13,<4.0
Classifier: Programming Language :: Python :: 3
Classifier: Programming Language :: Python :: 3.13
Classifier: Programming Language :: Python :: 3.14
Requires-Dist: httpx (>=0.28.1,<0.29.0)
Requires-Dist: loguru (>=0.7.3,<0.8.0)
Requires-Dist: p2d2 (>=0.1.110,<0.2.0)
Requires-Dist: pickleclass (>=0.1.0,<0.2.0)
Requires-Dist: pyperclip (>=1.9.0,<2.0.0)
Requires-Dist: toml (>=0.10.2,<0.11.0)
